{
    "dream": {
        "phDict": [
            "d",
            "r",
            "i",
            "ː",
            "m"
        ],
        "map": [
            0,
            0,
            1,
            1,
            0
        ]
    },
    "during": {
        "phDict": [
            "d",
            "u",
            "r",
            "i",
            "n",
            "g"
        ],
        "map": [
            2,
            0,
            0,
            0,
            0,
            0
        ]
    },
    "earth": {
        "phDict": [
            "e",
            "ɝ",
            "r",
            "θ",
            "h"
        ],
        "map": [
            0,
            1,
            0,
            1,
            0
        ]
    },
    "easy": {
        "phDict": [
            "e",
            "i",
            "z",
            "i"
        ],
        "map": [
            2,
            1,
            1,
            1
        ]
    },
    "eat": {
        "phDict": [
            "i",
            " ",
            " "
        ],
        "map": [
            1,
            0,
            0
        ]
    },
    "elephant": {
        "phDict": [
            "ɛ",
            "l",
            "ə",
            "p",
            "h",
            "ə",
            "n",
            "t"
        ],
        "map": [
            3,
            0,
            1,
            0,
            0,
            1,
            0,
            0
        ]
    },
    "enough": {
        "phDict": [
            "ɪ",
            "n",
            "ʌ",
            "u",
            "f",
            " "
        ],
        "map": [
            1,
            2,
            1,
            0,
            1,
            0
        ]
    },
    "every": {
        "phDict": [
            "ɛ",
            "v",
            "x",
            "r",
            "y"
        ],
        "map": [
            3,
            0,
            1,
            0,
            0
        ]
    },
    "everything": {
        "phDict": [
            "ɛ",
            "v",
            "x",
            "r",
            "y",
            "θ",
            "h",
            "i",
            "n",
            "g"
        ],
        "map": [
            3,
            0,
            1,
            0,
            0,
            1,
            0,
            0,
            0,
            0
        ]
    },
    "example": {
        "phDict": [
            "e",
            "x",
            "æ",
            "m",
            "p",
            "l",
            "e"
        ],
        "map": [
            0,
            2,
            1,
            0,
            0,
            0,
            0
        ]
    },
    "exist": {
        "phDict": [
            "ɪ",
            "x",
            "ɪ",
            " ",
            "t"
        ],
        "map": [
            1,
            2,
            1,
            0,
            0
        ]
    },
    "expensive": {
        "phDict": [
            "ɪ",
            "x",
            "p",
            "ɛ",
            "n",
            "s",
            "i",
            "v",
            "e"
        ],
        "map": [
            1,
            0,
            2,
            1,
            0,
            0,
            0,
            0,
            0
        ]
    },
    "explain": {
        "phDict": [
            "ɪ",
            "x",
            "p",
            "l",
            "e",
            "ɪ",
            "n"
        ],
        "map": [
            1,
            0,
            2,
            0,
            1,
            1,
            0
        ]
    },
    "face": {
        "phDict": [
            "f",
            "eɪ",
            "c",
            "e"
        ],
        "map": [
            0,
            1,
            0,
            0
        ]
    },
    "family": {
        "phDict": [
            "f",
            "æ",
            "(",
            "ə",
            ")",
            "y"
        ],
        "map": [
            2,
            1,
            1,
            1,
            1,
            0
        ]
    },
    "fantastic": {
        "phDict": [
            "f",
            "æ",
            "n",
            "t",
            "æ",
            "s",
            "t",
            "i",
            "c"
        ],
        "map": [
            0,
            1,
            0,
            2,
            1,
            0,
            0,
            0,
            0
        ]
    },
    "far": {
        "phDict": [
            "f",
            "ɑ",
            "r"
        ],
        "map": [
            0,
            1,
            0
        ]
    },
    "father": {
        "phDict": [
            "f",
            "ɑː",
            "ð",
            "h",
            "e",
            "r"
        ],
        "map": [
            0,
            1,
            1,
            0,
            0,
            0
        ]
    },
    "first": {
        "phDict": [
            "f",
            "ɝ",
            " ",
            "s",
            "t"
        ],
        "map": [
            0,
            1,
            0,
            0,
            0
        ]
    },
    "flower": {
        "phDict": [
            "f",
            "l",
            "a",
            "ʊ",
            "ɚ",
            "r"
        ],
        "map": [
            2,
            0,
            1,
            1,
            1,
            0
        ]
    },
    "fly": {
        "phDict": [
            "f",
            "l",
            "aɪ"
        ],
        "map": [
            0,
            0,
            1
        ]
    },
    "forest": {
        "phDict": [
            "f",
            "ɒ",
            "r",
            "ɪ",
            "s",
            "t"
        ],
        "map": [
            2,
            1,
            0,
            1,
            0,
            0
        ]
    },
    "forget": {
        "phDict": [
            "f",
            "ɚ",
            "r",
            "g",
            "ɛ",
            "t"
        ],
        "map": [
            0,
            1,
            0,
            2,
            1,
            0
        ]
    },
    "friend": {
        "phDict": [
            "f",
            "r",
            "ɛ",
            " ",
            "n",
            "d"
        ],
        "map": [
            0,
            0,
            1,
            0,
            0,
            0
        ]
    },
    "from": {
        "phDict": [
            "f",
            "r",
            "ʌ",
            "m"
        ],
        "map": [
            0,
            0,
            1,
            0
        ]
    },
    "funny": {
        "phDict": [
            "f",
            "ʌ",
            "n",
            "n",
            "y"
        ],
        "map": [
            2,
            1,
            0,
            0,
            0
        ]
    },
    "game": {
        "phDict": [
            "g",
            "eɪ",
            "m",
            "e"
        ],
        "map": [
            0,
            1,
            0,
            0
        ]
    },
    "geography": {
        "phDict": [
            "dʒ",
            "i",
            "ɑ",
            "g",
            "r",
            "a",
            "f",
            "h",
            "y"
        ],
        "map": [
            1,
            1,
            3,
            0,
            0,
            0,
            1,
            0,
            0
        ]
    },
    "give": {
        "phDict": [
            "g",
            " ",
            "v",
            "x"
        ],
        "map": [
            0,
            0,
            0,
            1
        ]
    },
    "go": {
        "phDict": [
            "g",
            "əʊ"
        ],
        "map": [
            0,
            1
        ]
    },
    "good": {
        "phDict": [
            "g",
            "ʊ",
            " ",
            "d"
        ],
        "map": [
            0,
            1,
            0,
            0
        ]
    },
    "grammar": {
        "phDict": [
            "g",
            "r",
            "æ",
            "m",
            "m",
            "ɚ",
            "r"
        ],
        "map": [
            2,
            0,
            1,
            0,
            0,
            1,
            0
        ]
    },
    "grass": {
        "phDict": [
            "g",
            "r",
            "ɑː",
            "s",
            "s"
        ],
        "map": [
            0,
            0,
            1,
            0,
            0
        ]
    },
    "hand": {
        "phDict": [
            "h",
            "æ",
            "n",
            "d"
        ],
        "map": [
            0,
            1,
            0,
            0
        ]
    },
    "happy": {
        "phDict": [
            "h",
            "æ",
            "p",
            "p",
            "y"
        ],
        "map": [
            2,
            1,
            0,
            0,
            0
        ]
    },
    "have": {
        "phDict": [
            "h",
            "æ",
            "v",
            "e"
        ],
        "map": [
            0,
            1,
            0,
            0
        ]
    },
    "hear": {
        "phDict": [
            "h",
            "ɪ",
            "ɚ",
            "r"
        ],
        "map": [
            0,
            1,
            1,
            0
        ]
    },
    "help": {
        "phDict": [
            "h",
            "ɛ",
            "l",
            "p"
        ],
        "map": [
            0,
            1,
            0,
            0
        ]
    },
    "here": {
        "phDict": [
            "h",
            "ɪ",
            "ɚ",
            " "
        ],
        "map": [
            0,
            1,
            1,
            0
        ]
    },
    "history": {
        "phDict": [
            "h",
            "i",
            "s",
            "(",
            "ə",
            ")",
            "y"
        ],
        "map": [
            2,
            0,
            0,
            1,
            1,
            1,
            0
        ]
    },
    "home": {
        "phDict": [
            "h",
            "əʊ",
            "m",
            "e"
        ],
        "map": [
            0,
            1,
            0,
            0
        ]
    },
    "horn": {
        "phDict": [
            "h",
            "ɔː",
            " ",
            "n"
        ],
        "map": [
            0,
            1,
            0,
            0
        ]
    },
    "house": {
        "phDict": [
            "h",
            "a",
            "ʊ",
            "s",
            "e"
        ],
        "map": [
            0,
            1,
            1,
            0,
            0
        ]
    },
    "how": {
        "phDict": [
            "h",
            "aʊ",
            " "
        ],
        "map": [
            0,
            1,
            0
        ]
    },
    "hundred": {
        "phDict": [
            "h",
            "ʌ",
            "n",
            "d",
            "r",
            "e",
            "d"
        ],
        "map": [
            2,
            1,
            0,
            0,
            0,
            0,
            0
        ]
    },
    "hungry": {
        "phDict": [
            "h",
            "ʌ",
            "n",
            "g",
            "r",
            "y"
        ],
        "map": [
            2,
            1,
            0,
            0,
            0,
            0
        ]
    },
    "idea": {
        "phDict": [
            "aɪ",
            "d",
            "iə",
            " "
        ],
        "map": [
            1,
            2,
            1,
            0
        ]
    },
    "imagine": {
        "phDict": [
            "i",
            "m",
            "a",
            "dʒ",
            "i",
            "n",
            "e"
        ],
        "map": [
            0,
            0,
            0,
            1,
            0,
            0,
            0
        ]
    },
    "information": {
        "phDict": [
            "ˌ",
            "n",
            "f",
            "ɚ",
            "r",
            "m",
            "eɪ",
            "ʃ",
            "ə",
            "o",
            "n"
        ],
        "map": [
            1,
            0,
            0,
            1,
            0,
            2,
            1,
            1,
            1,
            0,
            0
        ]
    },
    "inside": {
        "phDict": [
            "i",
            "n",
            "s",
            "aɪ",
            "d",
            "e"
        ],
        "map": [
            2,
            0,
            0,
            1,
            0,
            0
        ]
    },
    "interesting": {
        "phDict": [
            "ɪ",
            "n",
            "t",
            "ə",
            "r",
            "ə",
            "s",
            "t",
            "i",
            "n",
            "g"
        ],
        "map": [
            3,
            0,
            0,
            1,
            0,
            1,
            0,
            0,
            0,
            0,
            0
        ]
    },
    "job": {
        "phDict": [
            "dʒ",
            "ɒ",
            "b"
        ],
        "map": [
            1,
            1,
            0
        ]
    },
    "journey": {
        "phDict": [
            "dʒ",
            "ɝ",
            "u",
            "r",
            "n",
            "i",
            "y"
        ],
        "map": [
            3,
            1,
            0,
            0,
            0,
            1,
            0
        ]
    },
    "jump": {
        "phDict": [
            "dʒ",
            "ʌ",
            "m",
            "p"
        ],
        "map": [
            1,
            1,
            0,
            0
        ]
    },
    "know": {
        "phDict": [
            "x",
            "n",
            "o",
            "w"
        ],
        "map": [
            1,
            0,
            0,
            0
        ]
    },
    "land": {
        "phDict": [
            "l",
            "æ",
            "n",
            "d"
        ],
        "map": [
            0,
            1,
            0,
            0
        ]
    },
    "laugh": {
        "phDict": [
            "l",
            "æ",
            " ",
            "f",
            "h"
        ],
        "map": [
            0,
            1,
            0,
            1,
            0
        ]
    },
    "leader": {
        "phDict": [
            "l",
            "i",
            " ",
            "d",
            "e",
            "r"
        ],
        "map": [
            2,
            1,
            0,
            0,
            0,
            0
        ]
    },
    "learn": {
        "phDict": [
            "l",
            "ɜ",
            "ː",
            "r",
            "n"
        ],
        "map": [
            0,
            1,
            1,
            0,
            0
        ]
    },
    "life": {
        "phDict": [
            "l",
            "aɪ",
            "f",
            "e"
        ],
        "map": [
            0,
            1,
            0,
            0
        ]
    },
    "light": {
        "phDict": [
            "l",
            "aɪ",
            "x",
            "h",
            "t"
        ],
        "map": [
            0,
            1,
            1,
            0,
            1
        ]
    },
    "like": {
        "phDict": [
            "l",
            "aɪ",
            "k",
            "e"
        ],
        "map": [
            0,
            1,
            0,
            0
        ]
    },
    "little": {
        "phDict": [
            "l",
            "i",
            "t",
            "t",
            "l",
            "x"
        ],
        "map": [
            2,
            0,
            0,
            0,
            0,
            1
        ]
    },
    "live": {
        "phDict": [
            "l",
            "ɪ",
            "v",
            "e"
        ],
        "map": [
            0,
            1,
            0,
            0
        ]
    },
    "look": {
        "phDict": [
            "l",
            "ʊ",
            " ",
            "k"
        ],
        "map": [
            0,
            1,
            0,
            0
        ]
    },
    "lose": {
        "phDict": [
            "l",
            "uː",
            "s",
            "e"
        ],
        "map": [
            0,
            1,
            0,
            0
        ]
    },
    "lost": {
        "phDict": [
            "l",
            "ɒ",
            "s",
            "t"
        ],
        "map": [
            0,
            1,
            0,
            0
        ]
    },
    "lot": {
        "phDict": [
            "l",
            "ɒ",
            "t"
        ],
        "map": [
            0,
            1,
            0
        ]
    },
    "make": {
        "phDict": [
            "m",
            "eɪ",
            "k",
            "e"
        ],
        "map": [
            0,
            1,
            0,
            0
        ]
    },
    "many": {
        "phDict": [
            "m",
            "ɛ",
            "n",
            "y"
        ],
        "map": [
            0,
            1,
            0,
            0
        ]
    },
    "maybe": {
        "phDict": [
            "m",
            "e",
            "ɪ",
            "b",
            "i"
        ],
        "map": [
            0,
            1,
            1,
            0,
            1
        ]
    },
    "meet": {
        "phDict": [
            "m",
            "i",
            "ː",
            "t"
        ],
        "map": [
            0,
            1,
            1,
            0
        ]
    },
    "meeting": {
        "phDict": [
            "m",
            "i",
            " ",
            "t",
            "i",
            "n",
            "g"
        ],
        "map": [
            2,
            1,
            0,
            0,
            0,
            0,
            0
        ]
    },
    "middle": {
        "phDict": [
            "m",
            "i",
            "d",
            "ə",
            "l",
            "e"
        ],
        "map": [
            0,
            0,
            1,
            1,
            1,
            0
        ]
    },
    "mile": {
        "phDict": [
            "m",
            "aɪ",
            "l",
            "e"
        ],
        "map": [
            0,
            1,
            0,
            0
        ]
    },
    "mistake": {
        "phDict": [
            "m",
            "i",
            "s",
            "t",
            "eɪ",
            "k",
            "e"
        ],
        "map": [
            0,
            0,
            0,
            0,
            1,
            0,
            0
        ]
    },
    "model": {
        "phDict": [
            "m",
            "ɑ",
            "d",
            "x",
            "l"
        ],
        "map": [
            0,
            1,
            0,
            1,
            0
        ]
    },
    "moment": {
        "phDict": [
            "m",
            "oʊ",
            "m",
            "ə",
            "n",
            "t"
        ],
        "map": [
            0,
            1,
            0,
            1,
            0,
            0
        ]
    },
    "money": {
        "phDict": [
            "m",
            "ʌ",
            "n",
            "i",
            "y"
        ],
        "map": [
            2,
            1,
            0,
            1,
            0
        ]
    },
    "month": {
        "phDict": [
            "m",
            "ʌ",
            "n",
            "θ",
            "h"
        ],
        "map": [
            0,
            1,
            0,
            1,
            0
        ]
    },
    "morning": {
        "phDict": [
            "m",
            "o",
            "r",
            "n",
            "i",
            "n",
            "g"
        ],
        "map": [
            2,
            0,
            0,
            0,
            0,
            0,
            0
        ]
    },
    "much": {
        "phDict": [
            "m",
            "ʌ",
            "t",
            "ʃ"
        ],
        "map": [
            0,
            1,
            1,
            1
        ]
    },
    "mute": {
        "phDict": [
            "m",
            "juː",
            "t",
            "e"
        ],
        "map": [
            0,
            1,
            0,
            0
        ]
    },
    "name": {
        "phDict": [
            "n",
            "eɪ",
            "m",
            "e"
        ],
        "map": [
            0,
            1,
            0,
            0
        ]
    },
    "need": {
        "phDict": [
            "n",
            "i",
            "ː",
            "d"
        ],
        "map": [
            0,
            1,
            1,
            0
        ]
    }
}